[
    {
        "inputs": [],
        "name": "get_token_price",
        "outputs": [
            {
                "name": "current_price",
                "type": "felt"
            }
        ],
        "stateMutability": "view",
        "type": "function"
    },
    {
        "inputs": [],
        "name": "get_action",
        "outputs": [],
        "stateMutability": "view",
        "type": "function"
    },
    {
        "inputs": [],
        "name": "last_executed",
        "outputs": [
            {
                "name": "_result",
                "type": "felt"
            }
        ],
        "stateMutability": "view",
        "type": "function"
    },
    {
        "inputs": [],
        "name": "probeTask",
        "outputs": [
            {
                "name": "_taskReady",
                "type": "felt"
            }
        ],
        "stateMutability": "view",
        "type": "function"
    },
    {
        "inputs": [
            {
                "name": "_amount",
                "type": "felt"
            },
            {
                "name": "_periodicity",
                "type": "felt"
            }
        ],
        "name": "set_bot_params",
        "outputs": [],
        "type": "function"
    },
    {
        "inputs": [],
        "name": "executeTask",
        "outputs": [],
        "type": "function"
    }
]
